{
  "project_info": {
    "project_number": "620283424106",
    "project_id": "loneworkermobileapplication",
    "storage_bucket": "loneworkermobileapplication.firebasestorage.app"
  },
  "client": [
    {
      "client_info": {
        "mobilesdk_app_id": "1:620283424106:android:7d74da030a2890f4fb8913",
        "android_client_info": {
          "package_name": "com.loneworkermobileapplication"
        }
      },
      "oauth_client": [],
      "api_key": [
        {
          "current_key": "AIzaSyDKVEIaPIhZvfqrLU-2Zba58IVbaBNE5gE"
        }
      ],
      "services": {
        "appinvite_service": {
          "other_platform_oauth_client": []
        }
      }
    }
  ],
  "configuration_version": "1"
}